nPYc/__init__.py
nPYc/_toolboxPath.py
nPYc/StudyDesigns/Abbreviations.csv
nPYc/StudyDesigns/AssayParameters.json
nPYc/StudyDesigns/AssayParametersSchema.json
nPYc/StudyDesigns/BI-LISA_analyteGroups.json
nPYc/StudyDesigns/BI-LISA_reference_groups.json
nPYc/StudyDesigns/BI-LISA_reference_ranges.json
nPYc/StudyDesigns/BI-LISAref.csv
nPYc/StudyDesigns/DilutionSeries.csv
nPYc/StudyDesigns/ExactMasses.csv
nPYc/StudyDesigns/colours.json
nPYc/StudyDesigns/urine_quant_b_reference_groups.json
nPYc/StudyDesigns/BlankISATAB/blank-ms/a_npc-test-study_metabolite_profiling_mass_spectrometry.txt
nPYc/StudyDesigns/BlankISATAB/blank-ms/i_Investigation.txt
nPYc/StudyDesigns/BlankISATAB/blank-ms/s_NPC-Test-Study.txt
nPYc/StudyDesigns/BlankISATAB/blank-nmr/a_npc-test-study_metabolite_profiling_NMR_spectroscopy.txt
nPYc/StudyDesigns/BlankISATAB/blank-nmr/i_Investigation.txt
nPYc/StudyDesigns/BlankISATAB/blank-nmr/s_NPC-Test-Study.txt
nPYc/StudyDesigns/ISATABFieldMappings/MSFields.json
nPYc/StudyDesigns/ISATABFieldMappings/NMRFields.json
nPYc/StudyDesigns/SOP/AminoAcidMS.json
nPYc/StudyDesigns/SOP/BrukerBI-LISA.json
nPYc/StudyDesigns/SOP/BrukerBI-QUANT-PS.json
nPYc/StudyDesigns/SOP/BrukerQuant-UR.json
nPYc/StudyDesigns/SOP/Generic.json
nPYc/StudyDesigns/SOP/GenericMS.json
nPYc/StudyDesigns/SOP/GenericNMRblood.json
nPYc/StudyDesigns/SOP/GenericNMRurine.json
nPYc/StudyDesigns/SOP/NMR1Djresblood.json
nPYc/StudyDesigns/SOP/NMR1Djresurine.json
nPYc/StudyDesigns/SOP/OxylipinMS.json
nPYc/StudyDesigns/SOP/TryptophanMS.json
nPYc/Templates/ID_request_MS.html
nPYc/Templates/MS_BatchCorrectionAssessmentReport.html
nPYc/Templates/MS_BatchCorrectionSummaryReport.html
nPYc/Templates/MS_CorrelationToDilutionReport.html
nPYc/Templates/MS_FeatureSelectionReport.html
nPYc/Templates/MS_FeatureSummaryReport.html
nPYc/Templates/MS_FinalSummaryReport.html
nPYc/Templates/MS_FinalSummaryReport_Abridged.html
nPYc/Templates/MS_peakPantheR_FinalSummaryReport.html
nPYc/Templates/NMR_FinalSummaryReport.html
nPYc-2.0.dist-info/LICENSE.md
nPYc-2.0.dist-info/METADATA
nPYc-2.0.dist-info/WHEEL
nPYc-2.0.dist-info/top_level.txt
nPYc-2.0.dist-info/RECORD
