Metadata-Version: 2.1
Name: nPYc
Version: 2.0
Summary: National Phenome Centre toolbox
Home-page: https://github.com/phenomecentre/npyc-toolbox
Author: National Phenome Centre
Author-email: phenomecentre@imperial.ac.uk
License: MIT
Platform: UNKNOWN
Classifier: Programming Language :: Python
Classifier: Programming Language :: Python :: 3.9
Classifier: Intended Audience :: Science/Research
Classifier: License :: OSI Approved :: MIT License
Classifier: Operating System :: OS Independent
Classifier: Topic :: Scientific/Engineering :: Bio-Informatics
License-File: LICENSE.md
Requires-Dist: cycler>=0.10.0
Requires-Dist: iPython>=6.3.1
Requires-Dist: Jinja2>=3.0.1
Requires-Dist: lmfit>=0.9.7
Requires-Dist: matplotlib==3.5.2
Requires-Dist: networkx>=2.5.1
Requires-Dist: numpy~=1.23.3
Requires-Dist: openpyxl
Requires-Dist: pandas~=1.5.0
Requires-Dist: plotly>=3.1.0
Requires-Dist: pyChemometrics>=0.1
Requires-Dist: scikit-learn>=0.19.1
Requires-Dist: scipy>=1.1.0
Requires-Dist: seaborn>=0.8.1
Requires-Dist: setuptools>=39.1.0
Requires-Dist: statsmodels>=0.9.0
